netnovelcrawler/__init__.py
netnovelcrawler/core/__init__.py
netnovelcrawler/core/ciweimao.py
netnovelcrawler/core/corebase.py
netnovelcrawler/core/crawlercorefactory.py
netnovelcrawler/core/dingdianks_com.py
netnovelcrawler/core/n22biqu_com.py
netnovelcrawler/core/sfacg.py
netnovelcrawler/core/yeduku.py
netnovelcrawler/core/crawlerengine/__init__.py
netnovelcrawler/core/crawlerengine/normalhttp.py
netnovelcrawler/core/crawlerengine/selenium.py
netnovelcrawler/utils/__init__.py
netnovelcrawler/utils/ocr_util.py
netnovelcrawler/utils/screenshot_util.py
netnovelcrawler/utils/starter_stopper.py
netnovelcrawlertaskmgr/__init__.py
netnovelcrawlertaskmgr/taskmgr.py
netnovelcrawlertaskmgr/taskmgrui.py
netnovelcrawlertaskmgr/tqdm_pyqt.py
netnovelcrawler-0.0.2.dist-info/LICENSE
netnovelcrawler-0.0.2.dist-info/METADATA
netnovelcrawler-0.0.2.dist-info/WHEEL
netnovelcrawler-0.0.2.dist-info/entry_points.txt
netnovelcrawler-0.0.2.dist-info/top_level.txt
netnovelcrawler-0.0.2.dist-info/RECORD
