Metadata-Version: 2.1
Name: netnovelcrawler
Version: 0.0.2
Summary: Crawler framework to download Internet-novels from web.
Author-email: NovelReader <xxxx@hotmail.com>
License: MIT
Keywords: net novel,crawler
Classifier: Operating System :: OS Independent
Classifier: Programming Language :: Python :: 3
Classifier: Programming Language :: Python :: 3.9
Classifier: Programming Language :: Python :: 3.10
Classifier: Programming Language :: Python :: 3.11
Classifier: Programming Language :: Python :: 3.12
Classifier: Topic :: Utilities
Classifier: Programming Language :: Python :: Implementation :: CPython
Classifier: License :: OSI Approved :: MIT License
Classifier: Natural Language :: Chinese (Simplified)
License-File: LICENSE
Requires-Dist: beautifulsoup4
Requires-Dist: requests
Requires-Dist: setuptools
Requires-Dist: setuptools-scm
Requires-Dist: selenium
Requires-Dist: numpy
Requires-Dist: Pillow
Provides-Extra: gui
Requires-Dist: PyQt6; extra == "gui"
